geocat/comp/__init__.py
geocat/comp/climatologies.py
geocat/comp/deprecated.py
geocat/comp/fourier_filters.py
geocat/comp/gc_util.py
geocat/comp/gradient.py
geocat/comp/interpolation.py
geocat/comp/meteorology.py
geocat/comp/spherical.py
geocat/comp/stats.py
geocat_comp-2025.12.1.dist-info/licenses/LICENSE
geocat_comp-2025.12.1.dist-info/METADATA
geocat_comp-2025.12.1.dist-info/WHEEL
geocat_comp-2025.12.1.dist-info/top_level.txt
geocat_comp-2025.12.1.dist-info/RECORD
