Metadata-Version: 2.4
Name: geocat.comp
Version: 2025.12.1
Summary: GeoCAT-comp is the computational component of the GeoCAT project and provides implementations of computational functions for analysis of geosciences data
Author-email: GeoCAT Team <geocat@ucar.edu>
License-Expression: Apache-2.0
Project-URL: documentation, https://geocat-comp.readthedocs.io
Project-URL: issue-tracker, https://github.com/NCAR/geocat-comp/issues
Project-URL: source-code, https://github.com/NCAR/geocat-comp
Classifier: Operating System :: OS Independent
Classifier: Intended Audience :: Science/Research
Classifier: Programming Language :: Python
Classifier: Programming Language :: Python :: 3
Classifier: Programming Language :: Python :: 3.10
Classifier: Programming Language :: Python :: 3.11
Classifier: Programming Language :: Python :: 3.12
Classifier: Programming Language :: Python :: 3.13
Classifier: Topic :: Scientific/Engineering
Requires-Python: >=3.10
License-File: LICENSE
Requires-Dist: cf_xarray>=0.3.1
Requires-Dist: cftime
Requires-Dist: eofs
Requires-Dist: metpy
Requires-Dist: numpy
Requires-Dist: packaging
Requires-Dist: scipy
Requires-Dist: xarray
Requires-Dist: xskillscore>=0.0.17
Dynamic: license-file
